twdictquery/__init__.py
twdictquery/twdictquery.py
twdictquery-0.0.4.dist-info/LICENSE
twdictquery-0.0.4.dist-info/METADATA
twdictquery-0.0.4.dist-info/WHEEL
twdictquery-0.0.4.dist-info/top_level.txt
twdictquery-0.0.4.dist-info/RECORD
