Metadata-Version: 2.1
Name: twdictquery
Version: 0.0.4
Summary: Dictonary query search
Home-page: UNKNOWN
Author: Iyappan
Author-email: iyappan@trackerwave.com
License: UNKNOWN
Keywords: dictonary,query,search,dict search
Platform: UNKNOWN
Classifier: Development Status :: 1 - Planning
Classifier: Intended Audience :: Developers
Classifier: Programming Language :: Python :: 3
Classifier: Operating System :: Unix
Classifier: Operating System :: MacOS :: MacOS X
Classifier: Operating System :: Microsoft :: Windows
License-File: LICENSE
